LICENSE
README.md
pyproject.toml
setup.cfg
setup.py
src/authpolicy/__init__.py
src/authpolicy.egg-info/PKG-INFO
src/authpolicy.egg-info/SOURCES.txt
src/authpolicy.egg-info/dependency_links.txt
src/authpolicy.egg-info/requires.txt
src/authpolicy.egg-info/top_level.txt