Metadata-Version: 2.1
Name: authpolicy
Version: 0.1.1
Summary: Python SDK for AuthPolicy.com
Home-page: https://github.com/AuthPolicy/sdk-python
Author: Arpit Maheshwari
Author-email: hello@authpolicy.com
License: MIT
Keywords: auth policy,permissions,authentication,authorization,rbac,abac,permissions as service
Classifier: Programming Language :: Python :: 3
Classifier: License :: OSI Approved :: MIT License
Classifier: Operating System :: OS Independent
Requires-Python: >=3.6
License-File: LICENSE
